{
  "city": "P\u00fcttlingen",
  "coronaContacts": true,
  "country": "DE",
  "dateOfBirth": "1972-03-10",
  "email": "p.winkler@example.de",
  "firstName": "Petra",
  "fluImmunization": true,
  "gender": "female",
  "insuranceCompany": "Techniker Krankenkasse",
  "insuranceMembershipNumber": "T348265637",
  "lastName": "Winkler",
  "nationality": "deutsch",
  "phoneNumber": "0082547807",
  "preIllnesses": [
    "RESPIRATORY_DISEASE"
  ],
  "riskAreas": [
    "CONTACT_WITH_CORONA_CASE_WORK"
  ],
  "speedOfSymptomsOutbreak": "Langsam",
  "street": "B\u00fcckerheide 61",
  "symptoms": [
    "COUGH",
    "FEVER",
    "HEADACHE",
    "BACK_PAIN",
    "COLD",
    "NAUSEA",
    "DIFFICULTY_BREATHING",
    "LOSS_OF_SENSE_OF_SMELL_TASTE"
  ],
  "weakenedImmuneSystem": false,
  "zip": "66406"
}