{
  "city": "Freiburg",
  "coronaContacts": true,
  "dateOfBirth": "1928-09-07",
  "email": "k.schulze@web.de",
  "firstName": "Karl",
  "fluImmunization": false,
  "gender": "m\u00e4nnlich",
  "houseNumber": 76,
  "insuranceCompany": "Techniker Krankenkasse",
  "insuranceMembershipNumber": "R833303441",
  "lastName": "Schulze",
  "phoneNumber": "64100376137",
  "preIllnesses": [
    "Imunsystemschw\u00e4che"
  ],
  "riskAreas": [
    ""
  ],
  "speedOfSymptomsOutbreak": "Mittel",
  "street": "Nordtstra\u00dfe",
  "symptoms": [
    "Husten"
  ],
  "weakenedImmuneSystem": false,
  "zip": "1805526"
}