{"lastName": "Peters", "firstName": "Tim", "gender": "m\u00e4nnlich", "dateOfBirth": "1987-11-12 22", "email": "t.peters@gmail.de", "phoneNumber": "74724810590", "street": "B\u00fcckerheide", "houseNumber": 6, "zip": "31056984", "city": "K\u00f6ln", "insuranceCompany": "IKK Nord", "insuranceMembershipNumber": "S750324955", "fluImmunization": true, "speedOfSymptomsOutbreak": "Schnell", "symptoms": ["Schnupfen", "Halschmerzen", "Gelenkschmerzen", "Atemschwierigkeiten", "Husten", "Kopfschmerzen", "Fieber", "Erk\u00e4ltung"], "coronaContacts": true, "riskAreas": [""], "weakenedImmuneSystem": false, "preIllnesses": ["Imunsystemschw\u00e4che"]}