{
  "city": "Berlin",
  "coronaContacts": true,
  "dateOfBirth": "1997-03-24",
  "email": "h.schroeder@gmx.de",
  "firstName": "Hans",
  "fluImmunization": false,
  "gender": "male",
  "houseNumber": 39,
  "insuranceCompany": "DAK Gesundheit",
  "insuranceMembershipNumber": "C392168202",
  "lastName": "Schr\u00f6der",
  "phoneNumber": "10018366752",
  "preIllnesses": [
    "Imunsystemschw\u00e4che"
  ],
  "riskAreas": [
    "Madrid"
  ],
  "speedOfSymptomsOutbreak": "Schnell",
  "street": "Abbachstra\u00dfe",
  "symptoms": [
    "Gelenkschmerzen",
    "Atemschwierigkeiten",
    "Erk\u00e4ltung",
    "Kopfschmerzen",
    "Schnupfen",
    "Husten"
  ],
  "weakenedImmuneSystem": false,
  "zip": "5991022"
}