{
  "city": "K\u00f6ln",
  "coronaContacts": true,
  "dateOfBirth": "1954-09-03",
  "email": "f.richter@web.de",
  "firstName": "Franz",
  "fluImmunization": false,
  "gender": "male",
  "houseNumber": 65,
  "insuranceCompany": "AOK",
  "insuranceMembershipNumber": "E374843786",
  "lastName": "Richter",
  "nationality": "deutsch",
  "phoneNumber": "64535218101",
  "preIllnesses": [
    "Herz-Kreislauf"
  ],
  "riskAreas": [
    "New York"
  ],
  "speedOfSymptomsOutbreak": "Langsam",
  "street": "B\u00fcckerheide",
  "symptoms": [
    "Fieber",
    "Gelenkschmerzen"
  ],
  "weakenedImmuneSystem": false,
  "zip": "355102"
}