{
  "city": "Bous",
  "coronaContacts": true,
  "country": "DE",
  "dateOfBirth": "1948-09-18",
  "email": "d.wagner@example.de",
  "firstName": "Daniel",
  "fluImmunization": true,
  "gender": "male",
  "insuranceCompany": "IKK Nord",
  "insuranceMembershipNumber": "Y190945411",
  "lastName": "Wagner",
  "nationality": "deutsch",
  "phoneNumber": "8610158199",
  "preIllnesses": [
    "ADIPOSITAS"
  ],
  "riskAreas": [
    "STAY_IN_MEDICAL_FACILITY"
  ],
  "speedOfSymptomsOutbreak": "Schnell",
  "street": "Nordstra\u00dfe 41",
  "symptoms": [
    "COLD",
    "BACK_PAIN",
    "SHORTNESS_OF_BREATH"
  ],
  "weakenedImmuneSystem": false,
  "zip": "66604"
}