{"lastName": "Schulz", "firstName": "Susanne", "gender": "weiblich", "dateOfBirth": "1968-11-24", "email": "s.schulz@gmx.de", "phoneNumber": "11654091098", "street": "B\u00fcckerheide", "houseNumber": 62, "zip": "36855105", "city": "M\u00fcnchen", "insuranceCompany": "Techniker Krankenkasse", "insuranceMembershipNumber": "U607354148", "fluImmunization": false, "speedOfSymptomsOutbreak": "Langsam", "symptoms": ["Schnupfen", "Gelenkschmerzen", "Husten", "Halschmerzen", "Kopfschmerzen", "Atemschwierigkeiten", "Erk\u00e4ltung"], "coronaContacts": false, "riskAreas": ["New York"], "weakenedImmuneSystem": true, "preIllnesses": [""]}