{
  "city": "St. Wendel",
  "coronaContacts": true,
  "country": "DE",
  "dateOfBirth": "1945-03-06",
  "email": "a.winter@example.de",
  "firstName": "Anna",
  "fluImmunization": false,
  "gender": "female",
  "insuranceCompany": "KNAPPSCHAFT",
  "insuranceMembershipNumber": "P838586956",
  "lastName": "Winter",
  "nationality": "deutsch",
  "phoneNumber": "33060463103",
  "preIllnesses": [
    "SMOKING"
  ],
  "riskAreas": [
    "CONTACT_WITH_CORONA_CASE_PRIVATE"
  ],
  "speedOfSymptomsOutbreak": "Mittel",
  "street": "B\u00fcckerheide 26",
  "symptoms": [
    "HEADACHE",
    "LOSS_OF_SENSE_OF_SMELL_TASTE",
    "LOSS_OF_APPETITE"
  ],
  "weakenedImmuneSystem": false,
  "zip": "66127"
}