{
  "city": "Hamburg",
  "coronaContacts": false,
  "dateOfBirth": "2005-05-28",
  "email": "a.winter@web.de",
  "firstName": "Anna",
  "fluImmunization": false,
  "gender": "female",
  "houseNumber": 100,
  "insuranceCompany": "DAK Gesundheit",
  "insuranceMembershipNumber": "N664880035",
  "lastName": "Winter",
  "phoneNumber": "22842110020",
  "preIllnesses": [
    ""
  ],
  "riskAreas": [
    "Hubei"
  ],
  "speedOfSymptomsOutbreak": "Schnell",
  "street": "Abbachstra\u00dfe",
  "symptoms": [
    "Gelenkschmerzen"
  ],
  "weakenedImmuneSystem": true,
  "zip": "3950240"
}