{"lastName": "Bauer", "firstName": "Peter", "gender": "m\u00e4nnlich", "dateOfBirth": "1940-09-17 04", "email": "p.bauer@t-online.de", "phoneNumber": "610830110147", "street": "Aastwiete", "houseNumber": 2, "zip": "24361510", "city": "K\u00f6ln", "insuranceCompany": "KNAPPSCHAFT", "insuranceMembershipNumber": "A667905909", "fluImmunization": false, "speedOfSymptomsOutbreak": "Langsam", "symptoms": ["Kopfschmerzen", "Schnupfen", "Husten", "Fieber"], "coronaContacts": true, "riskAreas": ["Tirol"], "weakenedImmuneSystem": true, "preIllnesses": ["Herz-Kreislauf"]}