{
  "city": "Berlin",
  "coronaContacts": false,
  "dateOfBirth": "1951-03-09",
  "email": "k.klein@posteo.de",
  "firstName": "Kai",
  "fluImmunization": true,
  "gender": "m\u00e4nnlich",
  "houseNumber": 96,
  "insuranceCompany": "Barmer",
  "insuranceMembershipNumber": "M102314313",
  "lastName": "Klein",
  "phoneNumber": "73178101080",
  "preIllnesses": [
    "Herz-Kreislauf"
  ],
  "riskAreas": [
    "Hubei"
  ],
  "street": "Im KramersfeldAar\u00f6stra\u00dfe",
  "weakenedImmuneSystem": true,
  "zip": "3267736"
}