{
  "city": "Neunkirchen",
  "coronaContacts": true,
  "country": "DE",
  "dateOfBirth": "2004-08-05",
  "email": "t.schmitt@example.de",
  "firstName": "Tim",
  "fluImmunization": true,
  "gender": "male",
  "insuranceCompany": "Techniker Krankenkasse",
  "insuranceMembershipNumber": "T820256933",
  "lastName": "Schmitt",
  "nationality": "deutsch",
  "phoneNumber": "56103669411",
  "preIllnesses": [],
  "riskAreas": [],
  "speedOfSymptomsOutbreak": "Schnell",
  "street": "Poststra\u00dfe 7",
  "symptoms": [
    "LOSS_OF_SENSE_OF_SMELL_TASTE",
    "LOSS_OF_APPETITE",
    "NAUSEA",
    "WEIGHT_LOSS",
    "HEADACHE",
    "SHORTNESS_OF_BREATH",
    "FEVER",
    "MUSCLE_PAIN",
    "DIFFICULTY_BREATHING",
    "BACK_PAIN",
    "COLD"
  ],
  "weakenedImmuneSystem": false,
  "zip": "66053"
}