{
  "city": "M\u00fcnchen",
  "coronaContacts": true,
  "dateOfBirth": "1998-07-09",
  "email": "t.bauer@gmail.de",
  "firstName": "Tim",
  "fluImmunization": false,
  "gender": "male",
  "houseNumber": 100,
  "insuranceCompany": "KNAPPSCHAFT",
  "insuranceMembershipNumber": "G729624046",
  "lastName": "Bauer",
  "nationality": "deutsch",
  "phoneNumber": "3171103101090",
  "preIllnesses": [
    "Krebserkrankung"
  ],
  "riskAreas": [
    "GrandEst"
  ],
  "speedOfSymptomsOutbreak": "Langsam",
  "street": "Aarhusweg",
  "symptoms": [
    "Schnupfen",
    "Halschmerzen",
    "Atemschwierigkeiten",
    "Husten",
    "Gelenkschmerzen"
  ],
  "weakenedImmuneSystem": true,
  "zip": "53293"
}