{
  "city": "Bochum",
  "coronaContacts": false,
  "dateOfBirth": "1964-03-16",
  "email": "m.peters@gmx.de",
  "firstName": "Marie",
  "fluImmunization": false,
  "gender": "female",
  "houseNumber": 10,
  "insuranceCompany": "DAK Gesundheit",
  "insuranceMembershipNumber": "W627015393",
  "lastName": "Peters",
  "nationality": "deutsch",
  "phoneNumber": "3545494808",
  "preIllnesses": [
    "Krebserkrankung"
  ],
  "riskAreas": [
    "Tirol"
  ],
  "speedOfSymptomsOutbreak": "Langsam",
  "street": "Schernerweg",
  "symptoms": [
    "Atemschwierigkeiten"
  ],
  "weakenedImmuneSystem": true,
  "zip": "36783"
}