{"lastName": "Winter", "firstName": "Daniel", "gender": "m\u00e4nnlich", "dateOfBirth": "1935-04-19", "email": "d.winter@posteo.de", "phoneNumber": "3529042284", "street": "Haidth\u00f6heAarweg", "houseNumber": 14, "zip": "10020539", "city": "Kiel", "insuranceCompany": "AOK", "insuranceMembershipNumber": "F384936197", "fluImmunization": false, "speedOfSymptomsOutbreak": "Langsam", "symptoms": ["Fieber", "Kopfschmerzen", "Husten", "Erk\u00e4ltung", "Atemschwierigkeiten", "Gelenkschmerzen"], "coronaContacts": true, "riskAreas": ["Madrid"], "weakenedImmuneSystem": false, "preIllnesses": ["Herz-Kreislauf"]}