{"lastName": "Weber", "firstName": "Kai", "gender": "m\u00e4nnlich", "dateOfBirth": "1928-05-26 21", "email": "k.weber@gmail.de", "phoneNumber": "10905351032", "street": "Aarhusweg", "houseNumber": 56, "zip": "9424123", "city": "D\u00fcsseldorf", "insuranceCompany": "IKK Nord", "insuranceMembershipNumber": "E323271100", "fluImmunization": true, "speedOfSymptomsOutbreak": "Schnell", "symptoms": ["Husten", "Halschmerzen", "Kopfschmerzen"], "coronaContacts": false, "riskAreas": ["New York"], "weakenedImmuneSystem": true, "preIllnesses": ["Imunsystemschw\u00e4che"]}